setup.py
dnsd_dist/Binomialdistribution.py
dnsd_dist/Gaussiandistribution.py
dnsd_dist/Generaldistribution.py
dnsd_dist/__init__.py
dnsd_dist.egg-info/PKG-INFO
dnsd_dist.egg-info/SOURCES.txt
dnsd_dist.egg-info/dependency_links.txt
dnsd_dist.egg-info/not-zip-safe
dnsd_dist.egg-info/top_level.txt