Metadata-Version: 1.0
Name: dnsd-dist
Version: 0.1
Summary: Gaussian and Binomial distributions
Home-page: UNKNOWN
Author: Bello Musa
Author-email: musbell007@gmail.com
License: MIT
Platform: UNKNOWN
